alloypress/__init__.py
alloypress/ssg.py
alloypress/stylesheet.py
alloypress-0.1.5.dist-info/METADATA
alloypress-0.1.5.dist-info/WHEEL
alloypress-0.1.5.dist-info/licenses/LICENSE
alloypress-0.1.5.dist-info/RECORD
