Metadata-Version: 2.1
Name: alloypress
Version: 0.1.5
Summary: HTML/CSS-only Python SSG with support for LaTeX, syntax highlighting and sidenotes.
Project-URL: Homepage, https://github.com/tmychow/alloypress
Author-email: Trevor Chow <tmychow@gmail.com>
License-File: LICENSE
Classifier: License :: OSI Approved :: MIT License
Classifier: Operating System :: OS Independent
Classifier: Programming Language :: Python :: 3
Requires-Python: >=3.10
Requires-Dist: latex2mathml
Requires-Dist: markdown
Requires-Dist: pygments
Requires-Dist: pyyaml
